gserializer/__init__.py
gserializer/__main__.py
gserializer/Tools/Filter.py
gserializer/Tools/Reader.py
gserializer/Tools/__init__.py
gserializer-1.0.6.dist-info/METADATA
gserializer-1.0.6.dist-info/WHEEL
gserializer-1.0.6.dist-info/top_level.txt
gserializer-1.0.6.dist-info/RECORD
