Metadata-Version: 2.1
Name: gserializer
Version: 1.0.6
Summary: Retrieve and serialize a google sheet into tabular data object for easier list and array manipulations
Home-page: https://github.com/paulshaoyuqiao/google-sheets-serializer
Author: Paul Shao
Author-email: paulshaoyuqiao1@berkeley.edu
License: MIT
Platform: UNKNOWN
Classifier: License :: OSI Approved :: MIT License
Classifier: Programming Language :: Python :: 3
Classifier: Programming Language :: Python :: 3.6
Classifier: Programming Language :: Python :: 3.7
Requires-Dist: google-api-python-client
Requires-Dist: google-auth-httplib2
